{
    "actualitzat": {
        "dataUpdate": "2025-09-21T18:42:21.582003+02:00"
    },
    "client": {
        "nom": "912 Ramon Loureiro Alonso"
    },
    "plans": [
        {
            "nom": "Basic",
            "periode": "Mensual",
            "maxConsultes": 2000,
            "consultesRestants": 1994,
            "consultesRealitzades": 6
        },
        {
            "nom": "XEMA",
            "periode": "Mensual",
            "maxConsultes": 750,
            "consultesRestants": 694,
            "consultesRealitzades": 56
        },
        {
            "nom": "Prediccio",
            "periode": "Mensual",
            "maxConsultes": 100,
            "consultesRestants": 89,
            "consultesRealitzades": 11
        },
        {
            "nom": "Quota",
            "periode": "Mensual",
            "maxConsultes": 300,
            "consultesRestants": 292,
            "consultesRealitzades": 8
        }
    ]
}